__init__.py
pyscrapper/__init__.py
pyscrapper/scrapper.py
pyscrapper/utilities.py
pyscrapper/assembly/__init__.py
pyscrapper/assembly/managers.py
pyscrapper/assembly/observers.py
pyscrapper/assembly/urlloaders.py
pyscrapper/resources/__init__.py
pyscrapper/resources/phantomjs
pyscrapper/resources/resource_manager.py
pyscrapper-1.0.0.dist-info/LICENSE
pyscrapper-1.0.0.dist-info/METADATA
pyscrapper-1.0.0.dist-info/WHEEL
pyscrapper-1.0.0.dist-info/top_level.txt
pyscrapper-1.0.0.dist-info/RECORD
