Metadata-Version: 2.1
Name: pyscrapper
Version: 1.0.0
Summary: A configurable web scrapping tool
Home-page: https://github.com/pavanyekabote/pyscrapper
Author: Pavan Kumar Yekabote
License: MIT
Keywords: scrapping pyscrapper scrape webscrapping
Platform: UNKNOWN
Requires-Python: >=3
Requires-Dist: bs4 (==0.0.1)
Requires-Dist: selenium (==3.141.0)
Requires-Dist: urllib3 (==1.25.7)
Provides-Extra: doc
Requires-Dist: sphinx ; extra == 'doc'
Requires-Dist: sphinx-rtd-theme ; extra == 'doc'
